emencia_django_admin
