Metadata-Version: 1.0
Name: emencia-django-admin
Version: 0.3dev-r2314
Summary: This package adds some features on the django admin interface.
Home-page: UNKNOWN
Author: Lafaye Philippe, Fache Julien
Author-email: lafaye@emencia.com, jfache@emencia.com
License: GPLv3
Platform: UNKNOWN
Classifier: Development Status :: 4 - Beta
Classifier: Environment :: Web Environment
Classifier: Framework :: Django
Classifier: Intended Audience :: Developers
Classifier: License :: OSI Approved :: GNU General Public License (GPL)
Classifier: Operating System :: OS Independent
Classifier: Programming Language :: Python
Classifier: Topic :: Internet :: WWW/HTTP :: Site Management
